nonebot_plugin_adsblocker/__init__.py
nonebot_plugin_adsblocker/db_funcs.py
nonebot_plugin_adsblocker/utils.py
nonebot_plugin_adsblocker-0.1.4.dist-info/licenses/LICENSE
nonebot_plugin_adsblocker-0.1.4.dist-info/METADATA
nonebot_plugin_adsblocker-0.1.4.dist-info/WHEEL
nonebot_plugin_adsblocker-0.1.4.dist-info/top_level.txt
nonebot_plugin_adsblocker-0.1.4.dist-info/RECORD
