Metadata-Version: 2.4
Name: nonebot-plugin-adsblocker
Version: 0.1.4
Summary: NoneBot 广告屏蔽插件，支持AI检测和二维码识别
Author-email: Heartestrella <admin@neossh.top>
License: MIT
Project-URL: Homepage, https://github.com/Heartestrella/plugin-adsblocker
Project-URL: Repository, https://github.com/Heartestrella/plugin-adsblocker
Project-URL: Documentation, https://github.com/Heartestrella/plugin-adsblocker
Keywords: nonebot,nonebot2,adblock,advertisement,qrcode
Classifier: Development Status :: 4 - Beta
Classifier: Framework :: Robot Framework
Classifier: Framework :: Robot Framework :: Library
Classifier: License :: OSI Approved :: MIT License
Classifier: Operating System :: OS Independent
Classifier: Programming Language :: Python :: 3
Classifier: Programming Language :: Python :: 3.8
Classifier: Programming Language :: Python :: 3.9
Classifier: Programming Language :: Python :: 3.10
Classifier: Programming Language :: Python :: 3.11
Classifier: Topic :: Communications :: Chat
Classifier: Topic :: Software Development :: Libraries :: Python Modules
Requires-Python: >=3.8
License-File: LICENSE
Requires-Dist: nonebot2>=2.3.0
Requires-Dist: nonebot-adapter-onebot>=2.3.0
Requires-Dist: httpx>=0.24.0
Requires-Dist: nonebot-plugin-localstore>=0.7.0
Provides-Extra: dev
Requires-Dist: pytest>=6.0.0; extra == "dev"
Requires-Dist: black>=22.0.0; extra == "dev"
Requires-Dist: isort>=5.0.0; extra == "dev"
Dynamic: license-file
